robotchain/__init__.py
robotchain/board/__init__.py
robotchain/ros/__init__.py
robotchain/utils/__init__.py
robotchain/utils/list/__init__.py
robotchain/utils/loging/__init__.py
robotchain/utils/random/__init__.py
robotchain-1.0.7.dist-info/METADATA
robotchain-1.0.7.dist-info/WHEEL
robotchain-1.0.7.dist-info/top_level.txt
robotchain-1.0.7.dist-info/RECORD
