Metadata-Version: 2.1
Name: robotchain
Version: 1.0.7
Summary: Python development framework for robotchain.
Home-page: https://github.com/geekros/python_sdk
Author: MakerYang
Author-email: admin@wileho.com
Classifier: Programming Language :: Python :: 3
Classifier: License :: OSI Approved :: MIT License
Classifier: Operating System :: OS Independent
Requires-Python: >=3.7.5
